marionette_predeployed/__init__.py
marionette_predeployed/address.py
marionette_predeployed/marionette_generator.py
marionette_predeployed/py.typed
marionette_predeployed/upgradeable_marionette_generator.py
marionette_predeployed/artifacts/.keep
marionette_predeployed/artifacts/Marionette.json
marionette_predeployed-1.0.0.dist-info/METADATA
marionette_predeployed-1.0.0.dist-info/WHEEL
marionette_predeployed-1.0.0.dist-info/top_level.txt
marionette_predeployed-1.0.0.dist-info/RECORD
