Metadata-Version: 2.1
Name: marionette-predeployed
Version: 1.0.0
Summary: A tool for generating predeployed marionette smart contract
Home-page: https://github.com/skalenetwork/marionette
Author: Dmytro Stebaiev
Author-email: dmytro@skalelabs.com
License: UNKNOWN
Platform: UNKNOWN
Classifier: Programming Language :: Python :: 3
Classifier: License :: OSI Approved :: GNU Affero General Public License v3
Classifier: Operating System :: OS Independent
Requires-Python: >=3.7
Requires-Dist: predeployed-generator
